patrowl/__init__.py
patrowl/exceptions.py
patrowl_sdk-1.0.0.dist-info/LICENSE
patrowl_sdk-1.0.0.dist-info/METADATA
patrowl_sdk-1.0.0.dist-info/WHEEL
patrowl_sdk-1.0.0.dist-info/top_level.txt
patrowl_sdk-1.0.0.dist-info/RECORD
