Metadata-Version: 2.1
Name: patrowl-sdk
Version: 1.0.0
Summary: Python API SDK for PatrowlDashboard
Home-page: https://github.com/Patrowl/PatrowlSDK
Author: Patrowl SAS
Author-email: getsupport@patrowl.io
License: AGPLv3
Platform: UNKNOWN
